setup.cfg
setup.py
jsoncache/__init__.py
jsoncache/errors.py
jsoncache/fileio.py
jsoncache/jsoncache.py
jsoncache/utils.py
jsoncache.egg-info/PKG-INFO
jsoncache.egg-info/SOURCES.txt
jsoncache.egg-info/dependency_links.txt
jsoncache.egg-info/top_level.txt
tests/__init__.py
tests/delete.py
tests/get.py
tests/init.py
tests/put.py
tests/save.py
tests/testbase.py
tests/update_dict.py