Metadata-Version: 1.1
Name: jsoncache
Version: 0.0.3
Summary: Easy way to manipulate JSON file for Python
Home-page: https://github.com/arpitbbhayani/json-cache
Author: Arpit Bhayani
Author-email: arpit.b.bhayani@gmail.com
License: UNKNOWN
Download-URL: https://github.com/arpitbbhayani/json-cache
Keywords: json,cache
Platform: UNKNOWN
